nerdfonts/__init__.py
nerdfonts/icons.py
nerdfonts-1.0.1.dist-info/METADATA
nerdfonts-1.0.1.dist-info/RECORD
nerdfonts-1.0.1.dist-info/WHEEL
nerdfonts-1.0.1.dist-info/top_level.txt
