Metadata-Version: 2.1
Name: nerdfonts
Version: 1.0.1
Summary: Nerd Fonts for Python
Home-page: https://gitlab.com/ajeetdsouza/nerdfonts-python
Author: Ajeet D'Souza
Author-email: 98ajeet@gmail.com
Maintainer: Ajeet D'Souza
Maintainer-email: 98ajeet@gmail.com
License: GNU GPLv3
Platform: UNKNOWN
Classifier: Environment :: Console
Classifier: Intended Audience :: Developers
Classifier: Operating System :: POSIX
Classifier: Programming Language :: Python
